dict_delta_logger/__init__.py
dict_delta_logger/logger.py
tests/__init__.py
tests/test_logger.py
delta_logger-0.1.0.dist-info/LICENSE
delta_logger-0.1.0.dist-info/METADATA
delta_logger-0.1.0.dist-info/WHEEL
delta_logger-0.1.0.dist-info/top_level.txt
delta_logger-0.1.0.dist-info/RECORD
