Metadata-Version: 2.1
Name: delta_logger
Version: 0.1.0
Summary: A Python library for logging messages to JSON files with rotation and validation.
Home-page: https://github.com/YCHuang2112sub/dict_delta_logger
Author: Yu-Cheng Huang
Author-email: ychuang2@bu.edu
Classifier: Programming Language :: Python :: 3
Classifier: License :: OSI Approved :: MIT License
Classifier: Operating System :: OS Independent
Requires-Python: >=3.6
License-File: LICENSE
Requires-Dist: pydantic
